{
    "is_primary_data": true,
    "prop_rename": {},
    "prop_map": {
        "cell_type_ontology_term_id": {
            "value_map": {
                "unknown": "CL:0000003",
                "foveal cone photoreceptor": "CL:0000287",
                "peripheral cone photoreceptor": "CL:0000287"
            },
            "update_from": "cell_type"
        },
        "ethnicity_ontology_term_id": {
            "value_map": {
                "unknown": "unknown"
            },
            "update_from": "ethnicity"
        },
        "assay_ontology_term_id": {
            "value_map": {
                "10x v3 sequencing": "EFO:0009922"
            },
            "update_from": "assay"
        },
        "development_stage_ontology_term_id": {
            "value_map": {
                "fovea_donor_2": "HsapDv:0000148",
                "peripheral_donor_2": "HsapDv:0000148",
                "fovea_donor_3": "HsapDv:0000208",
                "peripheral_donor_3": "HsapDv:0000208",
                "fovea_donor_1": "HsapDv:0000215",
                "peripheral_donor_1": "HsapDv:0000215"
            },
            "update_from": "libraryID"
        }
    },
    "update_dtypes": {},
    "add_uns": {
        "X_normalization": ""
    },
    "remove_obs": [
        "region"
    ],
    "remove_uns": []
}